{"total":46,"pageSize":10,"pageCount":5,"data":[{"title":"微信浏览器播放音乐的坑","slug":"微信浏览器播放音乐的坑","date":"2017-10-30T07:37:36.000Z","updated":"2023-06-21T08:55:09.216Z","comments":true,"path":"api/articles/微信浏览器播放音乐的坑.json","excerpt":null,"keywords":null,"cover":null,"content":null,"raw":null,"categories":[{"name":"weChat","path":"api/categories/weChat.json"}],"tags":[{"name":"weChat","path":"api/tags/weChat.json"},{"name":"audio","path":"api/tags/audio.json"}]},{"title":"使用SASS","slug":"使用SASS","date":"2017-10-20T06:11:27.000Z","updated":"2023-06-21T08:55:09.215Z","comments":true,"path":"api/articles/使用SASS.json","excerpt":null,"keywords":null,"cover":null,"content":null,"raw":null,"categories":[{"name":"nodeJs","path":"api/categories/nodeJs.json"}],"tags":[{"name":"sass","path":"api/tags/sass.json"}]},{"title":"nodejs随笔--fs模块","slug":"模块","date":"2017-10-20T06:11:27.000Z","updated":"2023-06-21T08:55:09.216Z","comments":true,"path":"api/articles/模块.json","excerpt":null,"keywords":null,"cover":null,"content":null,"raw":null,"categories":[{"name":"nodeJs","path":"api/categories/nodeJs.json"}],"tags":[{"name":"nodeJs","path":"api/tags/nodeJs.json"},{"name":"fs模块","path":"api/tags/fs模块.json"}]},{"title":"github下fork后同步个人仓库和源仓库","slug":"github和gitlab下fork后同步个人仓库和源仓库","date":"2017-10-19T03:16:52.000Z","updated":"2023-06-21T08:55:09.213Z","comments":true,"path":"api/articles/github和gitlab下fork后同步个人仓库和源仓库.json","excerpt":null,"keywords":null,"cover":null,"content":null,"raw":null,"categories":[{"name":"git","path":"api/categories/git.json"}],"tags":[{"name":"git","path":"api/tags/git.json"},{"name":"gitHub","path":"api/tags/gitHub.json"}]},{"title":"git命令","slug":"git命令","date":"2017-09-25T02:10:23.000Z","updated":"2023-06-21T08:55:09.213Z","comments":true,"path":"api/articles/git命令.json","excerpt":null,"keywords":null,"cover":null,"content":null,"raw":null,"categories":[{"name":"git","path":"api/categories/git.json"}],"tags":[{"name":"git","path":"api/tags/git.json"}]},{"title":"css3选择器简介","slug":"hello-world","date":"2017-08-24T11:06:28.000Z","updated":"2023-06-21T08:55:09.213Z","comments":true,"path":"api/articles/hello-world.json","excerpt":null,"keywords":null,"cover":null,"content":null,"raw":null,"categories":[{"name":"css","path":"api/categories/css.json"}],"tags":[{"name":"css","path":"api/tags/css.json"}]}]}